CHANGELOG.rst
CONTRIBUTING.rst
MANIFEST.in
README.rst
VERSION
setup.py
RSTransaction.egg-info/PKG-INFO
RSTransaction.egg-info/SOURCES.txt
RSTransaction.egg-info/dependency_links.txt
RSTransaction.egg-info/top_level.txt
rstransaction/__init__.py
rstransaction/test_rstransaction.py
rstransaction/transaction_processor.py
rstransaction/transactional_registries.py