Metadata-Version: 2.2
Name: RSTransaction
Version: 0.3
Summary: Extendable transaction system, to build workflows with commit/rollback semantics.
Home-page: https://github.com/pakal/rstransaction
Author: Pascal Chambon
Author-email: pythoniks@gmail.com
License: http://www.opensource.org/licenses/mit-license.php
Platform: any
Classifier: Development Status :: 2 - Pre-Alpha
Classifier: Intended Audience :: Developers
Classifier: Intended Audience :: Information Technology
Classifier: License :: OSI Approved :: MIT License
Classifier: Programming Language :: Python
Classifier: Topic :: Software Development :: Libraries :: Python Modules
Classifier: Operating System :: Microsoft :: Windows
Classifier: Operating System :: Unix
Classifier: Operating System :: MacOS :: MacOS X
Dynamic: author
Dynamic: author-email
Dynamic: classifier
Dynamic: description
Dynamic: home-page
Dynamic: license
Dynamic: platform
Dynamic: summary
